paapi5_python_sdk/__init__.py
paapi5_python_sdk/api_client.py
paapi5_python_sdk/configuration.py
paapi5_python_sdk/rest.py
paapi5_python_sdk/api/__init__.py
paapi5_python_sdk/api/default_api.py
paapi5_python_sdk/auth/__init__.py
paapi5_python_sdk/auth/sign_helper.py
paapi5_python_sdk/models/__init__.py
paapi5_python_sdk/models/availability.py
paapi5_python_sdk/models/browse_node.py
paapi5_python_sdk/models/browse_node_ancestor.py
paapi5_python_sdk/models/browse_node_child.py
paapi5_python_sdk/models/browse_node_info.py
paapi5_python_sdk/models/browse_nodes_result.py
paapi5_python_sdk/models/by_line_info.py
paapi5_python_sdk/models/classifications.py
paapi5_python_sdk/models/condition.py
paapi5_python_sdk/models/content_info.py
paapi5_python_sdk/models/content_rating.py
paapi5_python_sdk/models/contributor.py
paapi5_python_sdk/models/customer_reviews.py
paapi5_python_sdk/models/delivery_flag.py
paapi5_python_sdk/models/dimension_based_attribute.py
paapi5_python_sdk/models/duration_price.py
paapi5_python_sdk/models/error_data.py
paapi5_python_sdk/models/external_ids.py
paapi5_python_sdk/models/get_browse_nodes_request.py
paapi5_python_sdk/models/get_browse_nodes_resource.py
paapi5_python_sdk/models/get_browse_nodes_response.py
paapi5_python_sdk/models/get_items_request.py
paapi5_python_sdk/models/get_items_resource.py
paapi5_python_sdk/models/get_items_response.py
paapi5_python_sdk/models/get_variations_request.py
paapi5_python_sdk/models/get_variations_resource.py
paapi5_python_sdk/models/get_variations_response.py
paapi5_python_sdk/models/image_size.py
paapi5_python_sdk/models/image_type.py
paapi5_python_sdk/models/images.py
paapi5_python_sdk/models/item.py
paapi5_python_sdk/models/item_id_type.py
paapi5_python_sdk/models/item_info.py
paapi5_python_sdk/models/items_result.py
paapi5_python_sdk/models/language_type.py
paapi5_python_sdk/models/languages.py
paapi5_python_sdk/models/manufacture_info.py
paapi5_python_sdk/models/max_price.py
amzn_brain_paapi5-1.1.0.dist-info/COPYING.txt
amzn_brain_paapi5-1.1.0.dist-info/LICENSE.txt
amzn_brain_paapi5-1.1.0.dist-info/METADATA
amzn_brain_paapi5-1.1.0.dist-info/NOTICE.txt
amzn_brain_paapi5-1.1.0.dist-info/WHEEL
amzn_brain_paapi5-1.1.0.dist-info/top_level.txt
amzn_brain_paapi5-1.1.0.dist-info/RECORD
