Metadata-Version: 2.1
Name: amzn-brain-paapi5
Version: 1.1.0
Summary: ProductAdvertisingAPI 5.0 Python SDK
Author: Amazon Product Advertising API Team
License: Apache License 2.0
Keywords: amzn-brain-paapi5
License-File: LICENSE.txt
License-File: COPYING.txt
License-File: NOTICE.txt
Requires-Dist: urllib3 >=1.15
Requires-Dist: six >=1.10
Requires-Dist: certifi
Requires-Dist: python-dateutil
